{
  "targets": {
    "double:debug": {
      "outFile": "../public/asmDouble/debug.wasm",
      "textFile": "../public/asmDouble/debug.wat",
      "sourceMap": true,
      "debug": true
    },
    "double:release": {
      "outFile": "../public/asmDouble/release.wasm",
      "textFile": "../public/asmDouble/release.wat",
      "sourceMap": true,
      "optimizeLevel": 3,
      "shrinkLevel": 0,
      "converge": false,
      "noAssert": false
    },
    "bigNum:debug": {
      "outFile": "../public/asmBigNum/debug.wasm",
      "textFile": "../public/asmBigNum/debug.wat",
      "sourceMap": true,
      "debug": true
    },
    "bigNum:release": {
      "outFile": "../public/asmBigNum/release.wasm",
      "textFile": "../public/asmBigNum/release.wat",
      "sourceMap": true,
      "optimizeLevel": 3,
      "shrinkLevel": 0,
      "converge": false,
      "noAssert": false
    }
  },
  "options": {
    "bindings": "raw",
    "importMemory": true,
    "optimizeLevel": 3,
    "runtime": "stub"
  }
}
